{"version":1,"resource":"file:///home/marion/Documents/angular-projects/trsn/translating/angular.json","entries":[{"id":"AtVn.json","timestamp":1715173005770},{"id":"EgJQ.json","timestamp":1715173817053},{"id":"sbcf.json","timestamp":1715174078864},{"id":"bb72.json","timestamp":1715174262114},{"id":"1noa.json","timestamp":1715174582915},{"id":"T17L.json","timestamp":1715175220363},{"id":"vfWY.json","timestamp":1715175446750},{"id":"jlwc.json","timestamp":1715175509455},{"id":"lSXP.json","timestamp":1715582485264},{"id":"1qh9.json","timestamp":1715586553044},{"id":"WUs3.json","timestamp":1715600910368},{"id":"JxDc.json","timestamp":1715602634445}]}